JavascriptXuexizhinanCYuyanBianchengWang/README.md
JavascriptXuexizhinanCYuyanBianchengWang/__init__.py
JavascriptXuexizhinanCYuyanBianchengWang/__main__.py
JavascriptXuexizhinanCYuyanBianchengWang/file.epub
JavascriptXuexizhinanCYuyanBianchengWang/index.html
JavascriptXuexizhinanCYuyanBianchengWang/css/__init__.py
JavascriptXuexizhinanCYuyanBianchengWang/css/annotations.css
JavascriptXuexizhinanCYuyanBianchengWang/css/main.css
JavascriptXuexizhinanCYuyanBianchengWang/css/normalize.css
JavascriptXuexizhinanCYuyanBianchengWang/css/popup.css
JavascriptXuexizhinanCYuyanBianchengWang/font/__init__.py
JavascriptXuexizhinanCYuyanBianchengWang/font/fontello.eot
JavascriptXuexizhinanCYuyanBianchengWang/font/fontello.svg
JavascriptXuexizhinanCYuyanBianchengWang/font/fontello.ttf
JavascriptXuexizhinanCYuyanBianchengWang/font/fontello.woff
JavascriptXuexizhinanCYuyanBianchengWang/img/__init__.py
JavascriptXuexizhinanCYuyanBianchengWang/img/annotator-glyph-sprite.png
JavascriptXuexizhinanCYuyanBianchengWang/img/annotator-icon-sprite.png
JavascriptXuexizhinanCYuyanBianchengWang/img/apple-touch-icon.png
JavascriptXuexizhinanCYuyanBianchengWang/img/cancelfullscreen.png
JavascriptXuexizhinanCYuyanBianchengWang/img/close.png
JavascriptXuexizhinanCYuyanBianchengWang/img/fullscreen.png
JavascriptXuexizhinanCYuyanBianchengWang/img/loader.gif
JavascriptXuexizhinanCYuyanBianchengWang/img/menu-icon.png
JavascriptXuexizhinanCYuyanBianchengWang/img/save.png
JavascriptXuexizhinanCYuyanBianchengWang/img/saved.png
JavascriptXuexizhinanCYuyanBianchengWang/img/settings-s.png
JavascriptXuexizhinanCYuyanBianchengWang/img/settings.png
JavascriptXuexizhinanCYuyanBianchengWang/img/star.png
JavascriptXuexizhinanCYuyanBianchengWang/js/__init__.py
JavascriptXuexizhinanCYuyanBianchengWang/js/epub.js
JavascriptXuexizhinanCYuyanBianchengWang/js/epub.min.js
JavascriptXuexizhinanCYuyanBianchengWang/js/epub.min.map
JavascriptXuexizhinanCYuyanBianchengWang/js/hooks.min.js
javascript_xuexizhinan_c_yuyan_biancheng_wang-2024.3.4.0.dist-info/METADATA
javascript_xuexizhinan_c_yuyan_biancheng_wang-2024.3.4.0.dist-info/WHEEL
javascript_xuexizhinan_c_yuyan_biancheng_wang-2024.3.4.0.dist-info/entry_points.txt
javascript_xuexizhinan_c_yuyan_biancheng_wang-2024.3.4.0.dist-info/top_level.txt
javascript_xuexizhinan_c_yuyan_biancheng_wang-2024.3.4.0.dist-info/RECORD
